solution_efe_client_member/__init__.py
solution_efe_client_member/memberService.py
solution_efe_client_member-1.0.0.dist-info/METADATA
solution_efe_client_member-1.0.0.dist-info/WHEEL
solution_efe_client_member-1.0.0.dist-info/top_level.txt
solution_efe_client_member-1.0.0.dist-info/RECORD
